{
  "musicClass": [
    {
      "name": "Piano",
      "description": "Learn piano.",
      "instructor": "Emily",
      "instrument": "Piano",
      "day_of_week": "Tuesdays",
      "students": 8,
      "price": 60,
      "status":"Active"
    },
    {
      "name": "Violin",
      "description": "Master violin.",
      "instructor": "Michael",
      "instrument": "Violin",
      "day_of_week": "Wednesdays",
      "students": 6,
      "price": 55,
      "status":"Active"
    },
    {
      "name": "Drums",
      "description": "Drum workshop.",
      "instructor": "Sarah",
      "instrument": "Drums",
      "day_of_week": "Saturdays",
      "students": 12,
      "price": 70,
      "status":"Active"
    },
    {
      "name": "Saxophone",
      "description": "Saxophone lessons.",
      "instructor": "Robert",
      "instrument": "Saxophone",
      "day_of_week": "Thursdays",
      "students": 7,
      "price": 65,
      "status":"Closed"
    },
    {
      "name": "Guitar",
      "description": "Guitar masterclass.",
      "instructor": "James",
      "instrument": "Guitar",
      "day_of_week": "Fridays",
      "students": 10,
      "price": 75,
      "status":"Closed"
    },
    {
      "name": "Bass",
      "description": "Groove with bass.",
      "instructor": "Maria",
      "instrument": "Bass",
      "day_of_week": "Mondays",
      "students": 6,
      "price": 70,
      "status":"Closed"
    },
    {
      "name": "Flute",
      "description": "Flute classes.",
      "instructor": "Daniel",
      "instrument": "Flute",
      "day_of_week": "Wednesdays",
      "students": 8,
      "price": 55,
      "status":"Archived"
    },
    {
      "name": "Trumpet",
      "description": "Trumpet workshop.",
      "instructor": "Laura",
      "instrument": "Trumpet",
      "day_of_week": "Saturdays",
      "students": 10,
      "price": 80,
      "status":"Archived"
    },
    {
      "name": "Voice",
      "description": "Singing training.",
      "instructor": "Mark",
      "instrument": "Vocals",
      "day_of_week": "Tuesdays",
      "students": 5,
      "price": 60,
      "status":"Archived"
    },
    {
      "name": "Keyboard",
      "description": "Keyboard lessons.",
      "instructor": "Anna",
      "instrument": "Keyboard",
      "day_of_week": "Mondays",
      "students": 7,
      "price": 50,
      "status":"Active"
    }
  ],
  "Enrolments": [
    {
      "EnrNo": "001",
      "SName": "Alice",
      "CName": "Math",
      "Fees": "1000",
      "EnrDate": "2023-09-15"
    },
    {
      "EnrNo": "002",
      "SName": "Bob",
      "CName": "History",
      "Fees": "800",
      "EnrDate": "2023-09-16"
    },
    {
      "EnrNo": "003",
      "SName": "Charlie",
      "CName": "English",
      "Fees": "1200",
      "EnrDate": "2023-09-17"
    },
    {
      "EnrNo": "004",
      "SName": "David",
      "CName": "Science",
      "Fees": "950",
      "EnrDate": "2023-09-18"
    },
    {
      "EnrNo": "005",
      "SName": "Eve",
      "CName": "Art",
      "Fees": "700",
      "EnrDate": "2023-09-19"
    }
  ],
  "BestStudents": [
    {
      "RegNo": "001",
      "FName": "Alice",
      "LName": "Smith",
      "Course": "Math",
      "TotalFees": "$1000",
      "EnrDate": "2023-09-15"
    },
    {
      "RegNo": "002",
      "FName": "Bob",
      "LName": "Johnson",
      "Course": "History",
      "TotalFees": "$800",
      "EnrDate": "2023-09-16"
    },
    {
      "RegNo": "003",
      "FName": "Charlie",
      "LName": "Brown",
      "Course": "English",
      "TotalFees": "$1200",
      "EnrDate": "2023-09-17"
    },
    {
      "RegNo": "004",
      "FName": "David",
      "LName": "Miller",
      "Course": "Science",
      "TotalFees": "$950",
      "EnrDate": "2023-09-18"
    },
    {
      "RegNo": "005",
      "FName": "Eve",
      "LName": "Davis",
      "Course": "Art",
      "TotalFees": "$700",
      "EnrDate": "2023-09-19"
    }
  ]
}